{"type":"PR","pr":{"number":2,"head":"25a1e3e8985cacbc51ec4b3ce567f778172d0f2b"},"user":"Valentine Erokhin","status":"draft","branch":"cms/posts/2020-03-28-вечерний-кофе-24-марта-2020/index","collection":"posts","commitMessage":"Create Posts “2020-03-28-вечерний-кофе-24-марта-2020/index”","title":"Вечерний кофе, 24 марта 2020 ","description":"No Description!","objects":{"entry":{"path":"content/posts/2020-03-28-вечерний-кофе-24-марта-2020/index.md","sha":"8d67d7d736f8b404aa99edaafb81c5f5fbfd62b6"},"files":[{"path":"content/posts/2020-03-28-вечерний-кофе-24-марта-2020/images/1585225688929_barsa.jpg","sha":"e369c849d5c92745a6f02e9158cb05b6e84e4784"}]},"timeStamp":"2020-03-28T16:47:53.580Z","version":"1"}